cntnr/__init__.py
cntnr/container_cli.py
cntnr-0.0.1.dist-info/LICENSE.txt
cntnr-0.0.1.dist-info/METADATA
cntnr-0.0.1.dist-info/WHEEL
cntnr-0.0.1.dist-info/entry_points.txt
cntnr-0.0.1.dist-info/top_level.txt
cntnr-0.0.1.dist-info/RECORD
